{
  "heroes": [
    {
      "id": "b557c7c0-b89c-4a68-a2c6-3b9a3de6c5e1",
      "name": "выфавфывыфа",
      "description": "ыфваыфваывфа",
      "element": "earth"
    },
    {
      "id": "0196c91d-3359-46fb-909c-167dd76211aa",
      "element": "water",
      "name": "фыва",
      "description": "фыва"
    },
    {
      "id": "78356228-0c09-49d2-988a-970b0a894034",
      "name": "Огонь",
      "description": "Жечь напалмом",
      "element": "fire"
    },
    {
      "id": "f6192d36-2127-4a35-9afa-e2ad6de80388",
      "name": "asdf",
      "description": "sadf",
      "element": "water"
    }
  ],
  "filters": [
    {
      "name": "Все",
      "value": "all",
      "className": "btn-outline-dark"
    },
    {
      "name": "Огонь",
      "value": "fire",
      "className": "btn-danger"
    },
    {
      "name": "Вода",
      "value": "water",
      "className": "btn-primary"
    },
    {
      "name": "Ветер",
      "value": "wind",
      "className": "btn-success"
    },
    {
      "name": "Земля",
      "value": "earth",
      "className": "btn-secondary"
    }
  ],
  "filters1": [
    "all",
    "fire",
    "water",
    "wind",
    "earth"
  ]
}